requests_oauthlib_dags/__init__.py
requests_oauthlib_dags/exception.py
requests_oauthlib_dags/session.py
requests_oauthlib_dags-0.1.0.dist-info/LICENSE
requests_oauthlib_dags-0.1.0.dist-info/METADATA
requests_oauthlib_dags-0.1.0.dist-info/WHEEL
requests_oauthlib_dags-0.1.0.dist-info/RECORD
